sciplex_flow/__init__.py
sciplex_flow/backend/__init__.py
sciplex_flow/backend/main.py
sciplex_flow/backend/adapters/__init__.py
sciplex_flow/backend/adapters/websocket_emitter.py
sciplex_flow/cli/__init__.py
sciplex_flow/cli/__main__.py
sciplex_flow/cli/server.py
sciplex_flow/frontend/dist/index.html
sciplex_flow/frontend/dist/sciplex.ico
sciplex_flow/frontend/dist/vite.svg
sciplex_flow/frontend/dist/assets/index-Dba93GHF.js
sciplex_flow/frontend/dist/assets/index-cwr2WmF2.css
sciplex_flow-0.1.4.dist-info/licenses/LICENSE
sciplex_flow-0.1.4.dist-info/METADATA
sciplex_flow-0.1.4.dist-info/WHEEL
sciplex_flow-0.1.4.dist-info/entry_points.txt
sciplex_flow-0.1.4.dist-info/top_level.txt
sciplex_flow-0.1.4.dist-info/RECORD
