Metadata-Version: 2.4
Name: sciplex-flow
Version: 0.1.4
Summary: Local web app for Sciplex visual programming - node-based data science workflows
Author-email: Sciplex Team <info@sciplex.de>
License: MIT
Project-URL: Homepage, https://sciplex.de/en/
Project-URL: Documentation, https://sciplex.de/en/
Project-URL: Repository, https://github.com/sciplex-app/sciplex_flow.git
Keywords: data-science,visual-programming,workflow,nodes,web-app
Classifier: Development Status :: 3 - Alpha
Classifier: Intended Audience :: Science/Research
Classifier: Intended Audience :: Developers
Classifier: License :: OSI Approved :: MIT License
Classifier: Programming Language :: Python :: 3
Classifier: Programming Language :: Python :: 3.11
Classifier: Programming Language :: Python :: 3.12
Classifier: Topic :: Scientific/Engineering
Classifier: Topic :: Software Development :: Libraries :: Python Modules
Requires-Python: >=3.11
License-File: LICENSE
Requires-Dist: sciplex-core>=0.1.1
Requires-Dist: fastapi>=0.104.0
Requires-Dist: uvicorn[standard]>=0.24.0
Requires-Dist: websockets>=12.0
Requires-Dist: pydantic[email]>=2.5.0
Requires-Dist: python-multipart>=0.0.6
Provides-Extra: dev
Requires-Dist: pytest>=8.0.0; extra == "dev"
Requires-Dist: ruff>=0.8.4; extra == "dev"
Requires-Dist: mypy>=1.13.0; extra == "dev"
Dynamic: license-file
